pypaze/__init__.py
pypaze/app.py
pypaze/cli.py
pypaze/hooks.py
pypaze/middleware.py
pypaze/routing.py
pypaze/utils.py
pypaze-0.1.0.dist-info/LICENSE
pypaze-0.1.0.dist-info/METADATA
pypaze-0.1.0.dist-info/WHEEL
pypaze-0.1.0.dist-info/entry_points.txt
pypaze-0.1.0.dist-info/top_level.txt
pypaze-0.1.0.dist-info/RECORD
