Metadata-Version: 2.1
Name: pypaze
Version: 0.1.0
Summary: A lightweight full-stack web framework on top of Flask
Home-page: https://github.com/vishal-singh-baraiya/pypaze
Author: Vishal Singh Baraiya
Author-email: realvixhal@gmail.com
Classifier: Programming Language :: Python :: 3
Classifier: License :: OSI Approved :: MIT License
Classifier: Operating System :: OS Independent
License-File: LICENSE
Requires-Dist: Flask
Requires-Dist: watchdog
Requires-Dist: click
Requires-Dist: pathlib
